README.md
setup.py
elaphure/__init__.py
elaphure/__main__.py
elaphure/config.py
elaphure/database.py
elaphure/generator.py
elaphure/urls.py
elaphure.egg-info/PKG-INFO
elaphure.egg-info/SOURCES.txt
elaphure.egg-info/dependency_links.txt
elaphure.egg-info/entry_points.txt
elaphure.egg-info/requires.txt
elaphure.egg-info/top_level.txt
elaphure/readers/markdown.py
elaphure/readers/wheezy.py
elaphure/sources/fs.py
elaphure/views/entry.py
elaphure/views/static.py
elaphure/writers/dry_run.py
elaphure/writers/fs.py
elaphure/writers/gh_pages.py